{
    "homeInfo": {
        "title": "Audio Quality Evaluation",
        "message": "Welcome to this audio quality evaluation test.\n\nYou will listen to 11 audio samples and answer 2 questions about each one.\nPlease use headphones and ensure you are in a quiet environment.\n\nFor each question, rate the audio on a scale from 1 (worst) to 7 (best).\n\nClick the button below when you are ready to begin.",
        "buttonText": "Start test"
    },
    "questions": [
        {
            "name": "Sample 1",
            "description": "Listen to the audio sample below and answer both questions.\n\nCAPTION:\n\n",
            "caption": "solo acoustic nylon string guitar playing in a fingerstyle Brazilian bossa nova style.",
            "id": 1,
            "anchors": null,
            "references": null,
            "testSignals": [
                "test_signals/reference.mp3",
                "test_signals/reference.mp3"
            ],
            "prompts": {
                "0": "How correct is the information in the caption with relation to the audio? Rate on a scale from 1 (worst, incorrect information) to 7 (best, accurate information)",
                "1": "Does this description contain information that is unrelated to the audio clip? Rate on a scale from 1 (entire caption completely unrelated to the audio clip) to 7 (completely related)"
            },
            "scale": {
                "type": "discrete",
                "alignment": "horizontal",
                "labels": [
                    "1 (worst)",
                    "2",
                    "3",
                    "4",
                    "5",
                    "6",
                    "7 (best)"
                ],
                "values": [
                    1,
                    2,
                    3,
                    4,
                    5,
                    6,
                    7
                ]
            },
            "shuffleTestSignals": false,
            "referenceEvaluated": false,
            "anchorEvaluated": false,
            "submitButtonText": "Next"
        },
        {
            "name": "Sample 2",
            "description": "Listen to the audio sample below and answer both questions.\n\nCAPTION:\n\n",
            "caption": "This performance features a violin playing melodic lines over the soft, flowing rhythm of an acoustic guitar. The gentle interplay between these two instruments creates a peaceful and serene atmosphere well-suited for relaxation. Recorded as part of a live duo concert, the piece blends classical technique with folk-like intimacy.",
            "id": 1,
            "anchors": null,
            "references": null,
            "testSignals": [
                "test_signals/example_24.mp3",
                "test_signals/example_24.mp3"
            ],
            "prompts": {
                "0": "How correct is the information in the caption with relation to the audio? Rate on a scale from 1 (worst, incorrect information) to 7 (best, accurate information)",
                "1": "Does this description contain information that is unrelated to the audio clip? Rate on a scale from 1 (entire caption completely unrelated to the audio clip) to 7 (completely related)"
            },
            "scale": {
                "type": "discrete",
                "alignment": "horizontal",
                "labels": [
                    "1 (worst)",
                    "2",
                    "3",
                    "4",
                    "5",
                    "6",
                    "7 (best)"
                ],
                "values": [
                    1,
                    2,
                    3,
                    4,
                    5,
                    6,
                    7
                ]
            },
            "shuffleTestSignals": false,
            "referenceEvaluated": false,
            "anchorEvaluated": false,
            "submitButtonText": "Next"
        },
        {
            "name": "Sample 3",
            "description": "Listen to the audio sample below and answer both questions.\n\nCAPTION:\n\n",
            "caption": "This instrumental track from the INNIT Project blends heavy metal and doom influences with a dark, ominous atmosphere. Distorted guitars and synthesizers combine to create a powerful, aggressive soundscape that evokes tension and foreboding. The overall mood suits a dark fantasy setting, reinforcing the piece's intense and hypnotic quality.",
            "id": 1,
            "anchors": null,
            "references": null,
            "testSignals": [
                "test_signals/example_25.mp3",
                "test_signals/example_25.mp3"
            ],
            "prompts": {
                "0": "How correct is the information in the caption with relation to the audio? Rate on a scale from 1 (worst, incorrect information) to 7 (best, accurate information)",
                "1": "Does this description contain information that is unrelated to the audio clip? Rate on a scale from 1 (entire caption completely unrelated to the audio clip) to 7 (completely related)"
            },
            "scale": {
                "type": "discrete",
                "alignment": "horizontal",
                "labels": [
                    "1 (worst)",
                    "2",
                    "3",
                    "4",
                    "5",
                    "6",
                    "7 (best)"
                ],
                "values": [
                    1,
                    2,
                    3,
                    4,
                    5,
                    6,
                    7
                ]
            },
            "shuffleTestSignals": false,
            "referenceEvaluated": false,
            "anchorEvaluated": false,
            "submitButtonText": "Next"
        },
        {
            "name": "Sample 4",
            "description": "Listen to the audio sample below and answer both questions.\n\nCAPTION:\n\n",
            "caption": "This segment is an instrumental fantasy soundtrack that relies on a choir, strings, and harpsichord to create a solemn, Baroque-era atmosphere. The music moves at a slow, steady pace driven by a percussive bass line, evoking a grand sense of awe suitable for cinematic scenes. Although the upload title suggests a pop standard by Elvis Presley, the audio itself features no vocals or electric instruments.",
            "id": 1,
            "anchors": null,
            "references": null,
            "testSignals": [
                "test_signals/example_26.mp3",
                "test_signals/example_26.mp3"
            ],
            "prompts": {
                "0": "How correct is the information in the caption with relation to the audio? Rate on a scale from 1 (worst, incorrect information) to 7 (best, accurate information)",
                "1": "Does this description contain information that is unrelated to the audio clip? Rate on a scale from 1 (entire caption completely unrelated to the audio clip) to 7 (completely related)"
            },
            "scale": {
                "type": "discrete",
                "alignment": "horizontal",
                "labels": [
                    "1 (worst)",
                    "2",
                    "3",
                    "4",
                    "5",
                    "6",
                    "7 (best)"
                ],
                "values": [
                    1,
                    2,
                    3,
                    4,
                    5,
                    6,
                    7
                ]
            },
            "shuffleTestSignals": false,
            "referenceEvaluated": false,
            "anchorEvaluated": false,
            "submitButtonText": "Next"
        },
        {
            "name": "Sample 5",
            "description": "Listen to the audio sample below and answer both questions.\n\nCAPTION:\n\n",
            "caption": "This segment is an instrumental vintage cartoon soundtrack featuring a lively and cheerful melody played by a full orchestra. The fast tempo and steady rhythm create a lighthearted, playful mood suitable for comedic scenes or classic animation.",
            "id": 1,
            "anchors": null,
            "references": null,
            "testSignals": [
                "test_signals/example_27.mp3",
                "test_signals/example_27.mp3"
            ],
            "prompts": {
                "0": "How correct is the information in the caption with relation to the audio? Rate on a scale from 1 (worst, incorrect information) to 7 (best, accurate information)",
                "1": "Does this description contain information that is unrelated to the audio clip? Rate on a scale from 1 (entire caption completely unrelated to the audio clip) to 7 (completely related)"
            },
            "scale": {
                "type": "discrete",
                "alignment": "horizontal",
                "labels": [
                    "1 (worst)",
                    "2",
                    "3",
                    "4",
                    "5",
                    "6",
                    "7 (best)"
                ],
                "values": [
                    1,
                    2,
                    3,
                    4,
                    5,
                    6,
                    7
                ]
            },
            "shuffleTestSignals": false,
            "referenceEvaluated": false,
            "anchorEvaluated": false,
            "submitButtonText": "Next"
        },
        {
            "name": "Sample 6",
            "description": "Listen to the audio sample below and answer both questions.\n\nCAPTION:\n\n",
            "caption": "This instrumental track blends fast-paced drum and bass rhythms with a strong electronic bass line, creating an intense and energetic atmosphere. The driving beat and futuristic synth sounds make it perfectly suited for high-stakes video game scenes like boss battles or rapid action sequences. While the music features a dark and heavy mood typical of experimental electronic genres, its relentless energy keeps the listener engaged from start to finish.",
            "id": 1,
            "anchors": null,
            "references": null,
            "testSignals": [
                "test_signals/example_28.mp3",
                "test_signals/example_28.mp3"
            ],
            "prompts": {
                "0": "How correct is the information in the caption with relation to the audio? Rate on a scale from 1 (worst, incorrect information) to 7 (best, accurate information)",
                "1": "Does this description contain information that is unrelated to the audio clip? Rate on a scale from 1 (entire caption completely unrelated to the audio clip) to 7 (completely related)"
            },
            "scale": {
                "type": "discrete",
                "alignment": "horizontal",
                "labels": [
                    "1 (worst)",
                    "2",
                    "3",
                    "4",
                    "5",
                    "6",
                    "7 (best)"
                ],
                "values": [
                    1,
                    2,
                    3,
                    4,
                    5,
                    6,
                    7
                ]
            },
            "shuffleTestSignals": false,
            "referenceEvaluated": false,
            "anchorEvaluated": false,
            "submitButtonText": "Next"
        },
        {
            "name": "Sample 7",
            "description": "Listen to the audio sample below and answer both questions.\n\nCAPTION:\n\n",
            "caption": "This instrumental segment creates a dark and ominous atmosphere through the use of a low-frequency drone, a high-pitched tone, and a mechanical hum. The piece builds suspense effectively, making it well-suited for a horror movie soundtrack or a scene depicting a mechanical breakdown in an industrial setting.",
            "id": 1,
            "anchors": null,
            "references": null,
            "testSignals": [
                "test_signals/example_29.mp3",
                "test_signals/example_29.mp3"
            ],
            "prompts": {
                "0": "How correct is the information in the caption with relation to the audio? Rate on a scale from 1 (worst, incorrect information) to 7 (best, accurate information)",
                "1": "Does this description contain information that is unrelated to the audio clip? Rate on a scale from 1 (entire caption completely unrelated to the audio clip) to 7 (completely related)"
            },
            "scale": {
                "type": "discrete",
                "alignment": "horizontal",
                "labels": [
                    "1 (worst)",
                    "2",
                    "3",
                    "4",
                    "5",
                    "6",
                    "7 (best)"
                ],
                "values": [
                    1,
                    2,
                    3,
                    4,
                    5,
                    6,
                    7
                ]
            },
            "shuffleTestSignals": false,
            "referenceEvaluated": false,
            "anchorEvaluated": false,
            "submitButtonText": "Next"
        },
        {
            "name": "Sample 8",
            "description": "Listen to the audio sample below and answer both questions.\n\nCAPTION:\n\n",
            "caption": "This segment is an amateur recording of a vocal choir singing without instrumental accompaniment. The performance feels cheerful and lively, driven by a strong rhythmic pattern enhanced with hand clapping.",
            "id": 1,
            "anchors": null,
            "references": null,
            "testSignals": [
                "test_signals/example_30.mp3",
                "test_signals/example_30.mp3"
            ],
            "prompts": {
                "0": "How correct is the information in the caption with relation to the audio? Rate on a scale from 1 (worst, incorrect information) to 7 (best, accurate information)",
                "1": "Does this description contain information that is unrelated to the audio clip? Rate on a scale from 1 (entire caption completely unrelated to the audio clip) to 7 (completely related)"
            },
            "scale": {
                "type": "discrete",
                "alignment": "horizontal",
                "labels": [
                    "1 (worst)",
                    "2",
                    "3",
                    "4",
                    "5",
                    "6",
                    "7 (best)"
                ],
                "values": [
                    1,
                    2,
                    3,
                    4,
                    5,
                    6,
                    7
                ]
            },
            "shuffleTestSignals": false,
            "referenceEvaluated": false,
            "anchorEvaluated": false,
            "submitButtonText": "Next"
        },
        {
            "name": "Sample 9",
            "description": "Listen to the audio sample below and answer both questions.\n\nCAPTION:\n\n",
            "caption": "This instrumental track features ambient synth pads that establish a serene and relaxing atmosphere. Its slow, steady rhythm creates a gentle pulse ideal for meditation or as calming background music.",
            "id": 1,
            "anchors": null,
            "references": null,
            "testSignals": [
                "test_signals/example_31.mp3",
                "test_signals/example_31.mp3"
            ],
            "prompts": {
                "0": "How correct is the information in the caption with relation to the audio? Rate on a scale from 1 (worst, incorrect information) to 7 (best, accurate information)",
                "1": "Does this description contain information that is unrelated to the audio clip? Rate on a scale from 1 (entire caption completely unrelated to the audio clip) to 7 (completely related)"
            },
            "scale": {
                "type": "discrete",
                "alignment": "horizontal",
                "labels": [
                    "1 (worst)",
                    "2",
                    "3",
                    "4",
                    "5",
                    "6",
                    "7 (best)"
                ],
                "values": [
                    1,
                    2,
                    3,
                    4,
                    5,
                    6,
                    7
                ]
            },
            "shuffleTestSignals": false,
            "referenceEvaluated": false,
            "anchorEvaluated": false,
            "submitButtonText": "Next"
        },
        {
            "name": "Sample 10",
            "description": "Listen to the audio sample below and answer both questions.\n\nCAPTION:\n\n",
            "caption": "This instrumental piece features a lively violin melody accompanied by flute, set against a rhythmic tabla background that creates an upbeat dance atmosphere. The track evokes an energetic mood suitable for an Indian-themed movie or television soundtrack, standing apart from the smoother jazz and saxophone styles often found in similar archival uploads.",
            "id": 1,
            "anchors": null,
            "references": null,
            "testSignals": [
                "test_signals/example_32.mp3",
                "test_signals/example_32.mp3"
            ],
            "prompts": {
                "0": "How correct is the information in the caption with relation to the audio? Rate on a scale from 1 (worst, incorrect information) to 7 (best, accurate information)",
                "1": "Does this description contain information that is unrelated to the audio clip? Rate on a scale from 1 (entire caption completely unrelated to the audio clip) to 7 (completely related)"
            },
            "scale": {
                "type": "discrete",
                "alignment": "horizontal",
                "labels": [
                    "1 (worst)",
                    "2",
                    "3",
                    "4",
                    "5",
                    "6",
                    "7 (best)"
                ],
                "values": [
                    1,
                    2,
                    3,
                    4,
                    5,
                    6,
                    7
                ]
            },
            "shuffleTestSignals": false,
            "referenceEvaluated": false,
            "anchorEvaluated": false,
            "submitButtonText": "Next"
        },
        {
            "name": "Sample 11",
            "description": "Listen to the audio sample below and answer both questions.\n\nCAPTION:\n\n",
            "caption": "This instrumental track blends a strong Latin influence with a steady drumming rhythm and a groovy, percussive bass line. Keyboard accompaniment adds complexity to the melody while driving the piece forward with an energetic dance groove. The overall mood feels romantic and passionate, making it suitable for a dramatic or uplifting movie soundtrack.",
            "id": 1,
            "anchors": null,
            "references": null,
            "testSignals": [
                "test_signals/example_33.mp3",
                "test_signals/example_33.mp3"
            ],
            "prompts": {
                "0": "How correct is the information in the caption with relation to the audio? Rate on a scale from 1 (worst, incorrect information) to 7 (best, accurate information)",
                "1": "Does this description contain information that is unrelated to the audio clip? Rate on a scale from 1 (entire caption completely unrelated to the audio clip) to 7 (completely related)"
            },
            "scale": {
                "type": "discrete",
                "alignment": "horizontal",
                "labels": [
                    "1 (worst)",
                    "2",
                    "3",
                    "4",
                    "5",
                    "6",
                    "7 (best)"
                ],
                "values": [
                    1,
                    2,
                    3,
                    4,
                    5,
                    6,
                    7
                ]
            },
            "shuffleTestSignals": false,
            "referenceEvaluated": false,
            "anchorEvaluated": false,
            "submitButtonText": "Next"
        }
    ]
}